LICENSE.txt
MANIFEST.in
README.md
requirements.txt
setup.cfg
setup.py
astro_bifrost.egg-info/PKG-INFO
astro_bifrost.egg-info/SOURCES.txt
astro_bifrost.egg-info/dependency_links.txt
astro_bifrost.egg-info/requires.txt
astro_bifrost.egg-info/top_level.txt
bifrost/.DS_Store
bifrost/__init__.py
bifrost/filters.py
bifrost/maths.py
bifrost/neural_network.py
bifrost/spectrum.py
bifrost/utils.py
bifrost/__pycache__/__init__.cpython-38.pyc
bifrost/__pycache__/__init__.cpython-39.pyc
bifrost/__pycache__/cli.cpython-38.pyc
bifrost/__pycache__/filters.cpython-38.pyc
bifrost/__pycache__/maths.cpython-38.pyc
bifrost/__pycache__/spectrum.cpython-38.pyc
bifrost/__pycache__/spectrum.cpython-39.pyc
bifrost/__pycache__/utils.cpython-38.pyc
bifrost/config/neural.net.toml
bifrost/config/observed.neural.net.toml