Metadata-Version: 2.1
Name: astro-bifrost
Version: 2.0.1
Summary: Correct, normalize, coadd, and stack spectra together.
Home-page: https://github.com/Michael-Reefe/bifrost
Author: Michael Reefe
Author-email: michael.reefe8@gmail.com
License: UNKNOWN
Platform: UNKNOWN
Classifier: Programming Language :: Python :: 3.8
Classifier: Operating System :: Unix
Requires-Python: >=3.7
License-File: LICENSE.txt
